st_checkbox_tree/__init__.py
st_checkbox_tree/frontend/.prettierrc
st_checkbox_tree/frontend/package-lock.json
st_checkbox_tree/frontend/package.json
st_checkbox_tree/frontend/tsconfig.json
st_checkbox_tree/frontend/build/asset-manifest.json
st_checkbox_tree/frontend/build/bootstrap.min.css
st_checkbox_tree/frontend/build/index.html
st_checkbox_tree/frontend/build/precache-manifest.d1ec924d2afd0f4915129f95ded00f5b.js
st_checkbox_tree/frontend/build/react-checkbox-tree.css
st_checkbox_tree/frontend/build/service-worker.js
st_checkbox_tree/frontend/build/font-awesome/css/font-awesome.css
st_checkbox_tree/frontend/build/font-awesome/css/font-awesome.min.css
st_checkbox_tree/frontend/build/font-awesome/fonts/FontAwesome.otf
st_checkbox_tree/frontend/build/font-awesome/fonts/fontawesome-webfont.eot
st_checkbox_tree/frontend/build/font-awesome/fonts/fontawesome-webfont.svg
st_checkbox_tree/frontend/build/font-awesome/fonts/fontawesome-webfont.ttf
st_checkbox_tree/frontend/build/font-awesome/fonts/fontawesome-webfont.woff
st_checkbox_tree/frontend/build/font-awesome/fonts/fontawesome-webfont.woff2
st_checkbox_tree/frontend/build/font-awesome/less/animated.less
st_checkbox_tree/frontend/build/font-awesome/less/bordered-pulled.less
st_checkbox_tree/frontend/build/font-awesome/less/core.less
st_checkbox_tree/frontend/build/font-awesome/less/fixed-width.less
st_checkbox_tree/frontend/build/font-awesome/less/font-awesome.less
st_checkbox_tree/frontend/build/font-awesome/less/icons.less
st_checkbox_tree/frontend/build/font-awesome/less/larger.less
st_checkbox_tree/frontend/build/font-awesome/less/list.less
st_checkbox_tree/frontend/build/font-awesome/less/mixins.less
st_checkbox_tree/frontend/build/font-awesome/less/path.less
st_checkbox_tree/frontend/build/font-awesome/less/rotated-flipped.less
st_checkbox_tree/frontend/build/font-awesome/less/screen-reader.less
st_checkbox_tree/frontend/build/font-awesome/less/stacked.less
st_checkbox_tree-1.0.2.dist-info/licenses/LICENSE
st_checkbox_tree-1.0.2.dist-info/METADATA
st_checkbox_tree-1.0.2.dist-info/WHEEL
st_checkbox_tree-1.0.2.dist-info/top_level.txt
st_checkbox_tree-1.0.2.dist-info/RECORD
