Metadata-Version: 2.4
Name: st-checkbox-tree
Version: 1.0.2
Summary: Streamlit checkbox tree component
Author: Peter van Lunteren
Author-email: 
Keywords: streamlit,checkbox,tree,hierarchical,component,tree-lines,visual-hierarchy
Classifier: Development Status :: 5 - Production/Stable
Classifier: Intended Audience :: Developers
Classifier: License :: OSI Approved :: MIT License
Classifier: Operating System :: OS Independent
Classifier: Programming Language :: Python :: 3
Classifier: Programming Language :: Python :: 3.6
Classifier: Programming Language :: Python :: 3.7
Classifier: Programming Language :: Python :: 3.8
Classifier: Programming Language :: Python :: 3.9
Classifier: Programming Language :: Python :: 3.10
Classifier: Programming Language :: Python :: 3.11
Classifier: Topic :: Software Development :: Libraries :: Python Modules
Classifier: Topic :: Scientific/Engineering :: Visualization
Requires-Python: >=3.6
License-File: LICENSE
Requires-Dist: streamlit>=0.63
Dynamic: license-file
Dynamic: requires-python
